<?xml version="1.0" encoding="UTF-8" standalone="no"?>
<DIAGRAMA ID="1" TIPO="tpLogico" UniversalUnicID="06E-A2-716A-A-51DE-6E-CE">
    <InfoDiagrama ID="1">
        <Versao Valor="3.2.0"/>
        <Autores/>
        <Observacao/>
        <Width Valor="4096"/>
        <Height Valor="4096"/>
        <Alinhamento_v Valor="50"/>
        <Alinhamento_h Valor="60"/>
        <Zoom Valor="75"/>
        <Fonte Estilo="1" Nome="Arial" Tamanho="12"/>
        <Localizacao Left="42" Top="27"/>
        <Realce Valor="false"/>
        <SeparatorSQL Valor=";"/>
        <Prefixo Valor=""/>
    </InfoDiagrama>
    <Tabela ID="2">
        <Bounds Height="149" Left="539" Top="331" Width="159"/>
        <DisablePainted Valor="false"/>
        <Texto>order</Texto>
        <Observacao/>
        <Dicionario/>
        <Fonte Estilo="1" Nome="Arial" Tamanho="12"/>
        <Ancorado Valor="false"/>
        <Delimite Valor="true"/>
        <Roundrect Valor="22"/>
        <Gradiente Valor="true"/>
        <GradienteStartColor Valor="0,0,0,255"/>
        <GradienteEndColor Valor="204,204,204,255"/>
        <CorBorda Valor="0,0,0,255"/>
        <GDirecao Valor="0"/>
        <Alfa Valor="25"/>
        <Autosize Valor="true"/>
        <Gradiente Valor="true"/>
        <GradienteStartColor Valor="0,0,0,255"/>
        <GradienteEndColor Valor="204,204,204,255"/>
        <GDirecao Valor="0"/>
        <Alfa Valor="25"/>
        <ShowDDL Valor="false"/>
        <ShowInPlain Valor="false"/>
        <MostrarConstraints Valor="true"/>
        <PlainIR Valor="true"/>
        <Campos>
            <Campo>
                <Texto>id_order</Texto>
                <Tipo>Number(5)</Tipo>
                <Complemento/>
                <Dicionario/>
                <Observacao/>
                <Key Valor="true"/>
                <Fkey Valor="false"/>
                <Unique Valor="false"/>
            </Campo>
            <Campo>
                <Texto>payment_method</Texto>
                <Tipo>String(7)</Tipo>
                <Complemento/>
                <Dicionario/>
                <Observacao/>
                <Key Valor="false"/>
                <Fkey Valor="false"/>
                <Unique Valor="false"/>
            </Campo>
            <Campo>
                <Texto>order_date</Texto>
                <Tipo>Number(8)</Tipo>
                <Complemento/>
                <Dicionario/>
                <Observacao/>
                <Key Valor="false"/>
                <Fkey Valor="false"/>
                <Unique Valor="false"/>
            </Campo>
            <Campo>
                <Texto>fk_client_id_client</Texto>
                <Tipo>Number(5)</Tipo>
                <Complemento/>
                <Dicionario/>
                <Observacao/>
                <Key Valor="false"/>
                <Fkey Valor="true"/>
                <Unique Valor="false"/>
            </Campo>
        </Campos>
        <Constraints>
            <Constraint>
                <Nome Valor=""/>
                <Nomeada Valor="false"/>
                <Tipo Valor="0"/>
                <Dicionario/>
                <Observacao/>
                <DdlOnUpdate/>
                <DdlOnDelete/>
                <LigacaoParaOrigem ID="-1"/>
                <ConstraintOrigem CamposDestino="[-1]" CamposOrigem="[0]" ID="-1,-1"/>
            </Constraint>
            <Constraint>
                <Nome Valor=""/>
                <Nomeada Valor="false"/>
                <Tipo Valor="2"/>
                <Dicionario/>
                <Observacao/>
                <DdlOnUpdate/>
                <DdlOnDelete>RESTRICT</DdlOnDelete>
                <LigacaoParaOrigem ID="21"/>
                <ConstraintOrigem CamposDestino="[3]" CamposOrigem="[3]" ID="3,0">IR chave primária</ConstraintOrigem>
            </Constraint>
        </Constraints>
    </Tabela>
    <Tabela ID="3">
        <Bounds Height="149" Left="479" Top="592" Width="150"/>
        <DisablePainted Valor="false"/>
        <Texto>client</Texto>
        <Observacao/>
        <Dicionario/>
        <Fonte Estilo="1" Nome="Arial" Tamanho="12"/>
        <Ancorado Valor="false"/>
        <Delimite Valor="true"/>
        <Roundrect Valor="22"/>
        <Gradiente Valor="true"/>
        <GradienteStartColor Valor="0,0,0,255"/>
        <GradienteEndColor Valor="204,204,204,255"/>
        <CorBorda Valor="0,0,0,255"/>
        <GDirecao Valor="0"/>
        <Alfa Valor="25"/>
        <Autosize Valor="true"/>
        <Gradiente Valor="true"/>
        <GradienteStartColor Valor="0,0,0,255"/>
        <GradienteEndColor Valor="204,204,204,255"/>
        <GDirecao Valor="0"/>
        <Alfa Valor="25"/>
        <ShowDDL Valor="false"/>
        <ShowInPlain Valor="false"/>
        <MostrarConstraints Valor="true"/>
        <PlainIR Valor="true"/>
        <Campos>
            <Campo>
                <Texto>delivery_address</Texto>
                <Tipo>String(30)</Tipo>
                <Complemento/>
                <Dicionario/>
                <Observacao/>
                <Key Valor="false"/>
                <Fkey Valor="false"/>
                <Unique Valor="false"/>
            </Campo>
            <Campo>
                <Texto>name</Texto>
                <Tipo>String(25)</Tipo>
                <Complemento/>
                <Dicionario/>
                <Observacao/>
                <Key Valor="false"/>
                <Fkey Valor="false"/>
                <Unique Valor="false"/>
            </Campo>
            <Campo>
                <Texto>email</Texto>
                <Tipo>String(256)</Tipo>
                <Complemento/>
                <Dicionario/>
                <Observacao/>
                <Key Valor="false"/>
                <Fkey Valor="false"/>
                <Unique Valor="false"/>
            </Campo>
            <Campo>
                <Texto>id_client</Texto>
                <Tipo>Number(5)</Tipo>
                <Complemento/>
                <Dicionario/>
                <Observacao/>
                <Key Valor="true"/>
                <Fkey Valor="false"/>
                <Unique Valor="false"/>
            </Campo>
        </Campos>
        <Constraints>
            <Constraint>
                <Nome Valor=""/>
                <Nomeada Valor="false"/>
                <Tipo Valor="0"/>
                <Dicionario/>
                <Observacao/>
                <DdlOnUpdate/>
                <DdlOnDelete/>
                <LigacaoParaOrigem ID="-1"/>
                <ConstraintOrigem CamposDestino="[-1]" CamposOrigem="[3]" ID="-1,-1"/>
            </Constraint>
        </Constraints>
    </Tabela>
    <Tabela ID="4">
        <Bounds Height="193" Left="1133" Top="217" Width="203"/>
        <DisablePainted Valor="false"/>
        <Texto>product</Texto>
        <Observacao/>
        <Dicionario/>
        <Fonte Estilo="1" Nome="Arial" Tamanho="12"/>
        <Ancorado Valor="false"/>
        <Delimite Valor="true"/>
        <Roundrect Valor="22"/>
        <Gradiente Valor="true"/>
        <GradienteStartColor Valor="0,0,0,255"/>
        <GradienteEndColor Valor="204,204,204,255"/>
        <CorBorda Valor="0,0,0,255"/>
        <GDirecao Valor="0"/>
        <Alfa Valor="25"/>
        <Autosize Valor="true"/>
        <Gradiente Valor="true"/>
        <GradienteStartColor Valor="0,0,0,255"/>
        <GradienteEndColor Valor="204,204,204,255"/>
        <GDirecao Valor="0"/>
        <Alfa Valor="25"/>
        <ShowDDL Valor="false"/>
        <ShowInPlain Valor="false"/>
        <MostrarConstraints Valor="true"/>
        <PlainIR Valor="true"/>
        <Campos>
            <Campo>
                <Texto>id_product</Texto>
                <Tipo>Number(5)</Tipo>
                <Complemento/>
                <Dicionario/>
                <Observacao/>
                <Key Valor="true"/>
                <Fkey Valor="false"/>
                <Unique Valor="false"/>
            </Campo>
            <Campo>
                <Texto>price</Texto>
                <Tipo>Number(1000)</Tipo>
                <Complemento/>
                <Dicionario/>
                <Observacao/>
                <Key Valor="false"/>
                <Fkey Valor="false"/>
                <Unique Valor="false"/>
            </Campo>
            <Campo>
                <Texto>name</Texto>
                <Tipo>String(25)</Tipo>
                <Complemento/>
                <Dicionario/>
                <Observacao/>
                <Key Valor="false"/>
                <Fkey Valor="false"/>
                <Unique Valor="false"/>
            </Campo>
            <Campo>
                <Texto>fk_provider_id_provider</Texto>
                <Tipo>Number(5)</Tipo>
                <Complemento/>
                <Dicionario/>
                <Observacao/>
                <Key Valor="false"/>
                <Fkey Valor="true"/>
                <Unique Valor="false"/>
            </Campo>
            <Campo>
                <Texto>fk_stock_id_stock</Texto>
                <Tipo>Number(5)</Tipo>
                <Complemento/>
                <Dicionario/>
                <Observacao/>
                <Key Valor="false"/>
                <Fkey Valor="true"/>
                <Unique Valor="false"/>
            </Campo>
            <Campo>
                <Texto>fk_category_id_category</Texto>
                <Tipo>Number(5)</Tipo>
                <Complemento/>
                <Dicionario/>
                <Observacao/>
                <Key Valor="false"/>
                <Fkey Valor="true"/>
                <Unique Valor="false"/>
            </Campo>
        </Campos>
        <Constraints>
            <Constraint>
                <Nome Valor=""/>
                <Nomeada Valor="false"/>
                <Tipo Valor="0"/>
                <Dicionario/>
                <Observacao/>
                <DdlOnUpdate/>
                <DdlOnDelete/>
                <LigacaoParaOrigem ID="-1"/>
                <ConstraintOrigem CamposDestino="[-1]" CamposOrigem="[0]" ID="-1,-1"/>
            </Constraint>
            <Constraint>
                <Nome Valor=""/>
                <Nomeada Valor="false"/>
                <Tipo Valor="2"/>
                <Dicionario/>
                <Observacao/>
                <DdlOnUpdate/>
                <DdlOnDelete>RESTRICT</DdlOnDelete>
                <LigacaoParaOrigem ID="24"/>
                <ConstraintOrigem CamposDestino="[3]" CamposOrigem="[0]" ID="5,0">IR chave primária</ConstraintOrigem>
            </Constraint>
            <Constraint>
                <Nome Valor=""/>
                <Nomeada Valor="false"/>
                <Tipo Valor="2"/>
                <Dicionario/>
                <Observacao/>
                <DdlOnUpdate/>
                <DdlOnDelete>RESTRICT</DdlOnDelete>
                <LigacaoParaOrigem ID="27"/>
                <ConstraintOrigem CamposDestino="[4]" CamposOrigem="[0]" ID="6,0">IR chave primária</ConstraintOrigem>
            </Constraint>
            <Constraint>
                <Nome Valor=""/>
                <Nomeada Valor="false"/>
                <Tipo Valor="2"/>
                <Dicionario/>
                <Observacao/>
                <DdlOnUpdate/>
                <DdlOnDelete>RESTRICT</DdlOnDelete>
                <LigacaoParaOrigem ID="30"/>
                <ConstraintOrigem CamposDestino="[5]" CamposOrigem="[0]" ID="7,0">IR chave primária</ConstraintOrigem>
            </Constraint>
        </Constraints>
    </Tabela>
    <Tabela ID="5">
        <Bounds Height="127" Left="1133" Top="607" Width="150"/>
        <DisablePainted Valor="false"/>
        <Texto>provider</Texto>
        <Observacao/>
        <Dicionario/>
        <Fonte Estilo="1" Nome="Arial" Tamanho="12"/>
        <Ancorado Valor="false"/>
        <Delimite Valor="true"/>
        <Roundrect Valor="22"/>
        <Gradiente Valor="true"/>
        <GradienteStartColor Valor="0,0,0,255"/>
        <GradienteEndColor Valor="204,204,204,255"/>
        <CorBorda Valor="0,0,0,255"/>
        <GDirecao Valor="0"/>
        <Alfa Valor="25"/>
        <Autosize Valor="true"/>
        <Gradiente Valor="true"/>
        <GradienteStartColor Valor="0,0,0,255"/>
        <GradienteEndColor Valor="204,204,204,255"/>
        <GDirecao Valor="0"/>
        <Alfa Valor="25"/>
        <ShowDDL Valor="false"/>
        <ShowInPlain Valor="false"/>
        <MostrarConstraints Valor="true"/>
        <PlainIR Valor="true"/>
        <Campos>
            <Campo>
                <Texto>id_provider</Texto>
                <Tipo>Number(5)</Tipo>
                <Complemento/>
                <Dicionario/>
                <Observacao/>
                <Key Valor="true"/>
                <Fkey Valor="false"/>
                <Unique Valor="false"/>
            </Campo>
            <Campo>
                <Texto>contact</Texto>
                <Tipo>Number(11)</Tipo>
                <Complemento/>
                <Dicionario/>
                <Observacao/>
                <Key Valor="false"/>
                <Fkey Valor="false"/>
                <Unique Valor="false"/>
            </Campo>
            <Campo>
                <Texto>name</Texto>
                <Tipo>String(25)</Tipo>
                <Complemento/>
                <Dicionario/>
                <Observacao/>
                <Key Valor="false"/>
                <Fkey Valor="false"/>
                <Unique Valor="false"/>
            </Campo>
        </Campos>
        <Constraints>
            <Constraint>
                <Nome Valor=""/>
                <Nomeada Valor="false"/>
                <Tipo Valor="0"/>
                <Dicionario/>
                <Observacao/>
                <DdlOnUpdate/>
                <DdlOnDelete/>
                <LigacaoParaOrigem ID="-1"/>
                <ConstraintOrigem CamposDestino="[-1]" CamposOrigem="[0]" ID="-1,-1"/>
            </Constraint>
        </Constraints>
    </Tabela>
    <Tabela ID="6">
        <Bounds Height="105" Left="1452" Top="221" Width="185"/>
        <DisablePainted Valor="false"/>
        <Texto>stock</Texto>
        <Observacao/>
        <Dicionario/>
        <Fonte Estilo="1" Nome="Arial" Tamanho="12"/>
        <Ancorado Valor="false"/>
        <Delimite Valor="true"/>
        <Roundrect Valor="22"/>
        <Gradiente Valor="true"/>
        <GradienteStartColor Valor="0,0,0,255"/>
        <GradienteEndColor Valor="204,204,204,255"/>
        <CorBorda Valor="0,0,0,255"/>
        <GDirecao Valor="0"/>
        <Alfa Valor="25"/>
        <Autosize Valor="true"/>
        <Gradiente Valor="true"/>
        <GradienteStartColor Valor="0,0,0,255"/>
        <GradienteEndColor Valor="204,204,204,255"/>
        <GDirecao Valor="0"/>
        <Alfa Valor="25"/>
        <ShowDDL Valor="false"/>
        <ShowInPlain Valor="false"/>
        <MostrarConstraints Valor="true"/>
        <PlainIR Valor="true"/>
        <Campos>
            <Campo>
                <Texto>id_stock</Texto>
                <Tipo>Number(5)</Tipo>
                <Complemento/>
                <Dicionario/>
                <Observacao/>
                <Key Valor="true"/>
                <Fkey Valor="false"/>
                <Unique Valor="false"/>
            </Campo>
            <Campo>
                <Texto>avaliable_quantity</Texto>
                <Tipo>Number(1000)</Tipo>
                <Complemento/>
                <Dicionario/>
                <Observacao/>
                <Key Valor="false"/>
                <Fkey Valor="false"/>
                <Unique Valor="false"/>
            </Campo>
        </Campos>
        <Constraints>
            <Constraint>
                <Nome Valor=""/>
                <Nomeada Valor="false"/>
                <Tipo Valor="0"/>
                <Dicionario/>
                <Observacao/>
                <DdlOnUpdate/>
                <DdlOnDelete/>
                <LigacaoParaOrigem ID="-1"/>
                <ConstraintOrigem CamposDestino="[-1]" CamposOrigem="[0]" ID="-1,-1"/>
            </Constraint>
        </Constraints>
    </Tabela>
    <Tabela ID="7">
        <Bounds Height="105" Left="1502" Top="559" Width="150"/>
        <DisablePainted Valor="false"/>
        <Texto>category</Texto>
        <Observacao/>
        <Dicionario/>
        <Fonte Estilo="1" Nome="Arial" Tamanho="12"/>
        <Ancorado Valor="false"/>
        <Delimite Valor="true"/>
        <Roundrect Valor="22"/>
        <Gradiente Valor="true"/>
        <GradienteStartColor Valor="0,0,0,255"/>
        <GradienteEndColor Valor="204,204,204,255"/>
        <CorBorda Valor="0,0,0,255"/>
        <GDirecao Valor="0"/>
        <Alfa Valor="25"/>
        <Autosize Valor="true"/>
        <Gradiente Valor="true"/>
        <GradienteStartColor Valor="0,0,0,255"/>
        <GradienteEndColor Valor="204,204,204,255"/>
        <GDirecao Valor="0"/>
        <Alfa Valor="25"/>
        <ShowDDL Valor="false"/>
        <ShowInPlain Valor="false"/>
        <MostrarConstraints Valor="true"/>
        <PlainIR Valor="true"/>
        <Campos>
            <Campo>
                <Texto>id_category</Texto>
                <Tipo>Number(5)</Tipo>
                <Complemento/>
                <Dicionario/>
                <Observacao/>
                <Key Valor="true"/>
                <Fkey Valor="false"/>
                <Unique Valor="false"/>
            </Campo>
            <Campo>
                <Texto>name</Texto>
                <Tipo>String(25)</Tipo>
                <Complemento/>
                <Dicionario/>
                <Observacao/>
                <Key Valor="false"/>
                <Fkey Valor="false"/>
                <Unique Valor="false"/>
            </Campo>
        </Campos>
        <Constraints>
            <Constraint>
                <Nome Valor=""/>
                <Nomeada Valor="false"/>
                <Tipo Valor="0"/>
                <Dicionario/>
                <Observacao/>
                <DdlOnUpdate/>
                <DdlOnDelete/>
                <LigacaoParaOrigem ID="-1"/>
                <ConstraintOrigem CamposDestino="[-1]" CamposOrigem="[0]" ID="-1,-1"/>
            </Constraint>
        </Constraints>
    </Tabela>
    <Tabela ID="8">
        <Bounds Height="127" Left="366" Top="821" Width="174"/>
        <DisablePainted Valor="false"/>
        <Texto>Regular_client</Texto>
        <Observacao/>
        <Dicionario/>
        <Fonte Estilo="1" Nome="Arial" Tamanho="12"/>
        <Ancorado Valor="false"/>
        <Delimite Valor="true"/>
        <Roundrect Valor="22"/>
        <Gradiente Valor="true"/>
        <GradienteStartColor Valor="0,0,0,255"/>
        <GradienteEndColor Valor="204,204,204,255"/>
        <CorBorda Valor="0,0,0,255"/>
        <GDirecao Valor="0"/>
        <Alfa Valor="25"/>
        <Autosize Valor="true"/>
        <Gradiente Valor="true"/>
        <GradienteStartColor Valor="0,0,0,255"/>
        <GradienteEndColor Valor="204,204,204,255"/>
        <GDirecao Valor="0"/>
        <Alfa Valor="25"/>
        <ShowDDL Valor="false"/>
        <ShowInPlain Valor="false"/>
        <MostrarConstraints Valor="true"/>
        <PlainIR Valor="true"/>
        <Campos>
            <Campo>
                <Texto>loyalty_discount</Texto>
                <Tipo>Number(100)</Tipo>
                <Complemento/>
                <Dicionario/>
                <Observacao/>
                <Key Valor="false"/>
                <Fkey Valor="false"/>
                <Unique Valor="false"/>
            </Campo>
            <Campo>
                <Texto>register_date</Texto>
                <Tipo>Number(8)</Tipo>
                <Complemento/>
                <Dicionario/>
                <Observacao/>
                <Key Valor="false"/>
                <Fkey Valor="false"/>
                <Unique Valor="false"/>
            </Campo>
            <Campo>
                <Texto>fk_client_id_client</Texto>
                <Tipo>Number(5)</Tipo>
                <Complemento/>
                <Dicionario/>
                <Observacao/>
                <Key Valor="true"/>
                <Fkey Valor="true"/>
                <Unique Valor="false"/>
            </Campo>
        </Campos>
        <Constraints>
            <Constraint>
                <Nome Valor=""/>
                <Nomeada Valor="false"/>
                <Tipo Valor="0"/>
                <Dicionario/>
                <Observacao/>
                <DdlOnUpdate/>
                <DdlOnDelete/>
                <LigacaoParaOrigem ID="-1"/>
                <ConstraintOrigem CamposDestino="[-1]" CamposOrigem="[2]" ID="-1,-1"/>
            </Constraint>
            <Constraint>
                <Nome Valor=""/>
                <Nomeada Valor="false"/>
                <Tipo Valor="2"/>
                <Dicionario/>
                <Observacao/>
                <DdlOnUpdate/>
                <DdlOnDelete>CASCADE</DdlOnDelete>
                <LigacaoParaOrigem ID="12"/>
                <ConstraintOrigem CamposDestino="[2]" CamposOrigem="[3]" ID="3,0">IR chave primária</ConstraintOrigem>
            </Constraint>
        </Constraints>
    </Tabela>
    <Tabela ID="9">
        <Bounds Height="149" Left="823" Top="821" Width="158"/>
        <DisablePainted Valor="false"/>
        <Texto>corp_client</Texto>
        <Observacao/>
        <Dicionario/>
        <Fonte Estilo="1" Nome="Arial" Tamanho="12"/>
        <Ancorado Valor="false"/>
        <Delimite Valor="true"/>
        <Roundrect Valor="22"/>
        <Gradiente Valor="true"/>
        <GradienteStartColor Valor="0,0,0,255"/>
        <GradienteEndColor Valor="204,204,204,255"/>
        <CorBorda Valor="0,0,0,255"/>
        <GDirecao Valor="0"/>
        <Alfa Valor="25"/>
        <Autosize Valor="true"/>
        <Gradiente Valor="true"/>
        <GradienteStartColor Valor="0,0,0,255"/>
        <GradienteEndColor Valor="204,204,204,255"/>
        <GDirecao Valor="0"/>
        <Alfa Valor="25"/>
        <ShowDDL Valor="false"/>
        <ShowInPlain Valor="false"/>
        <MostrarConstraints Valor="true"/>
        <PlainIR Valor="true"/>
        <Campos>
            <Campo>
                <Texto>company_name</Texto>
                <Tipo>String(25)</Tipo>
                <Complemento/>
                <Dicionario/>
                <Observacao/>
                <Key Valor="false"/>
                <Fkey Valor="false"/>
                <Unique Valor="false"/>
            </Campo>
            <Campo>
                <Texto>credit_limit</Texto>
                <Tipo>String(10)</Tipo>
                <Complemento/>
                <Dicionario/>
                <Observacao/>
                <Key Valor="false"/>
                <Fkey Valor="false"/>
                <Unique Valor="false"/>
            </Campo>
            <Campo>
                <Texto>CNPJ</Texto>
                <Tipo>Number(14)</Tipo>
                <Complemento/>
                <Dicionario/>
                <Observacao/>
                <Key Valor="false"/>
                <Fkey Valor="false"/>
                <Unique Valor="false"/>
            </Campo>
            <Campo>
                <Texto>fk_client_id_client</Texto>
                <Tipo>Number(5)</Tipo>
                <Complemento/>
                <Dicionario/>
                <Observacao/>
                <Key Valor="true"/>
                <Fkey Valor="true"/>
                <Unique Valor="false"/>
            </Campo>
        </Campos>
        <Constraints>
            <Constraint>
                <Nome Valor=""/>
                <Nomeada Valor="false"/>
                <Tipo Valor="0"/>
                <Dicionario/>
                <Observacao/>
                <DdlOnUpdate/>
                <DdlOnDelete/>
                <LigacaoParaOrigem ID="-1"/>
                <ConstraintOrigem CamposDestino="[-1]" CamposOrigem="[3]" ID="-1,-1"/>
            </Constraint>
            <Constraint>
                <Nome Valor=""/>
                <Nomeada Valor="false"/>
                <Tipo Valor="2"/>
                <Dicionario/>
                <Observacao/>
                <DdlOnUpdate/>
                <DdlOnDelete>CASCADE</DdlOnDelete>
                <LigacaoParaOrigem ID="15"/>
                <ConstraintOrigem CamposDestino="[3]" CamposOrigem="[3]" ID="3,0">IR chave primária</ConstraintOrigem>
            </Constraint>
        </Constraints>
    </Tabela>
    <Tabela ID="10">
        <Bounds Height="127" Left="513" Top="1028" Width="150"/>
        <DisablePainted Valor="false"/>
        <Texto>vip_cleint</Texto>
        <Observacao/>
        <Dicionario/>
        <Fonte Estilo="1" Nome="Arial" Tamanho="12"/>
        <Ancorado Valor="false"/>
        <Delimite Valor="true"/>
        <Roundrect Valor="22"/>
        <Gradiente Valor="true"/>
        <GradienteStartColor Valor="0,0,0,255"/>
        <GradienteEndColor Valor="204,204,204,255"/>
        <CorBorda Valor="0,0,0,255"/>
        <GDirecao Valor="0"/>
        <Alfa Valor="25"/>
        <Autosize Valor="true"/>
        <Gradiente Valor="true"/>
        <GradienteStartColor Valor="0,0,0,255"/>
        <GradienteEndColor Valor="204,204,204,255"/>
        <GDirecao Valor="0"/>
        <Alfa Valor="25"/>
        <ShowDDL Valor="false"/>
        <ShowInPlain Valor="false"/>
        <MostrarConstraints Valor="true"/>
        <PlainIR Valor="true"/>
        <Campos>
            <Campo>
                <Texto>register_date</Texto>
                <Tipo>Number(8)</Tipo>
                <Complemento/>
                <Dicionario/>
                <Observacao/>
                <Key Valor="false"/>
                <Fkey Valor="false"/>
                <Unique Valor="false"/>
            </Campo>
            <Campo>
                <Texto>vip_level</Texto>
                <Tipo>Number(10)</Tipo>
                <Complemento/>
                <Dicionario/>
                <Observacao/>
                <Key Valor="false"/>
                <Fkey Valor="false"/>
                <Unique Valor="false"/>
            </Campo>
            <Campo>
                <Texto>fk_client_id_client</Texto>
                <Tipo>Number(5)</Tipo>
                <Complemento/>
                <Dicionario/>
                <Observacao/>
                <Key Valor="true"/>
                <Fkey Valor="true"/>
                <Unique Valor="false"/>
            </Campo>
        </Campos>
        <Constraints>
            <Constraint>
                <Nome Valor=""/>
                <Nomeada Valor="false"/>
                <Tipo Valor="0"/>
                <Dicionario/>
                <Observacao/>
                <DdlOnUpdate/>
                <DdlOnDelete/>
                <LigacaoParaOrigem ID="-1"/>
                <ConstraintOrigem CamposDestino="[-1]" CamposOrigem="[2]" ID="-1,-1"/>
            </Constraint>
            <Constraint>
                <Nome Valor=""/>
                <Nomeada Valor="false"/>
                <Tipo Valor="2"/>
                <Dicionario/>
                <Observacao/>
                <DdlOnUpdate/>
                <DdlOnDelete>CASCADE</DdlOnDelete>
                <LigacaoParaOrigem ID="18"/>
                <ConstraintOrigem CamposDestino="[2]" CamposOrigem="[3]" ID="3,0">IR chave primária</ConstraintOrigem>
            </Constraint>
        </Constraints>
    </Tabela>
    <Tabela ID="11">
        <Bounds Height="127" Left="823" Top="331" Width="224"/>
        <DisablePainted Valor="false"/>
        <Texto>product_order_place_order</Texto>
        <Observacao/>
        <Dicionario/>
        <Fonte Estilo="1" Nome="Arial" Tamanho="12"/>
        <Ancorado Valor="false"/>
        <Delimite Valor="true"/>
        <Roundrect Valor="22"/>
        <Gradiente Valor="true"/>
        <GradienteStartColor Valor="0,0,0,255"/>
        <GradienteEndColor Valor="204,204,204,255"/>
        <CorBorda Valor="0,0,0,255"/>
        <GDirecao Valor="0"/>
        <Alfa Valor="25"/>
        <Autosize Valor="true"/>
        <Gradiente Valor="true"/>
        <GradienteStartColor Valor="0,0,0,255"/>
        <GradienteEndColor Valor="204,204,204,255"/>
        <GDirecao Valor="0"/>
        <Alfa Valor="25"/>
        <ShowDDL Valor="false"/>
        <ShowInPlain Valor="false"/>
        <MostrarConstraints Valor="true"/>
        <PlainIR Valor="true"/>
        <Campos>
            <Campo>
                <Texto>quantity</Texto>
                <Tipo>Number(100)</Tipo>
                <Complemento/>
                <Dicionario/>
                <Observacao/>
                <Key Valor="false"/>
                <Fkey Valor="false"/>
                <Unique Valor="false"/>
            </Campo>
            <Campo>
                <Texto>fk_order_id_order</Texto>
                <Tipo>Number(5)</Tipo>
                <Complemento/>
                <Dicionario/>
                <Observacao/>
                <Key Valor="false"/>
                <Fkey Valor="true"/>
                <Unique Valor="false"/>
            </Campo>
            <Campo>
                <Texto>fk_product_id_product</Texto>
                <Tipo>Number(5)</Tipo>
                <Complemento/>
                <Dicionario/>
                <Observacao/>
                <Key Valor="false"/>
                <Fkey Valor="true"/>
                <Unique Valor="false"/>
            </Campo>
        </Campos>
        <Constraints>
            <Constraint>
                <Nome Valor=""/>
                <Nomeada Valor="false"/>
                <Tipo Valor="2"/>
                <Dicionario/>
                <Observacao/>
                <DdlOnUpdate/>
                <DdlOnDelete/>
                <LigacaoParaOrigem ID="-1"/>
                <ConstraintOrigem CamposDestino="[1]" CamposOrigem="[0]" ID="2,0">IR chave primária</ConstraintOrigem>
            </Constraint>
            <Constraint>
                <Nome Valor=""/>
                <Nomeada Valor="false"/>
                <Tipo Valor="2"/>
                <Dicionario/>
                <Observacao/>
                <DdlOnUpdate/>
                <DdlOnDelete/>
                <LigacaoParaOrigem ID="-1"/>
                <ConstraintOrigem CamposDestino="[2]" CamposOrigem="[0]" ID="4,0">IR chave primária</ConstraintOrigem>
            </Constraint>
        </Constraints>
    </Tabela>
    <LogicoLinha ID="12">
        <DisablePainted Valor="false"/>
        <Tag LinhaMestre="-1"/>
        <Dashed Valor="false"/>
        <Ancorado Valor="false"/>
        <TemSetaPontaA Valor="false"/>
        <TemSetaPontaB Valor="true"/>
        <SetaAberta Valor="true"/>
        <SetaLargura Valor="10"/>
        <Inteligente Valor="true"/>
        <SetaAutomatica Valor="true"/>
        <Largura Valor="1"/>
        <Ligacoes PontaA="3" PontaB="8"/>
        <Pontos>
            <Ponto Left="532" Top="738"/>
            <Ponto Left="532" Top="778"/>
            <Ponto Left="441" Top="778"/>
            <Ponto Left="441" Top="817"/>
        </Pontos>
        <LogicoCardinalidade ID="13">
            <Bounds Height="14" Left="495" Top="748" Width="39"/>
            <DisablePainted Valor="false"/>
            <Texto>Cardinalidade_1</Texto>
            <Observacao/>
            <Dicionario/>
            <Fonte Estilo="1" Nome="Arial" Tamanho="12"/>
            <Ancorado Valor="false"/>
            <TamanhoAutmatico Valor="true"/>
            <Card Valor="0"/>
            <MovimentacaoManual Valor="false"/>
            <Papel Valor=""/>
            <Fonte Estilo="1" Nome="Arial" Tamanho="12"/>
        </LogicoCardinalidade>
        <LogicoCardinalidade ID="14">
            <Bounds Height="14" Left="404" Top="799" Width="39"/>
            <DisablePainted Valor="false"/>
            <Texto>Cardinalidade_2</Texto>
            <Observacao/>
            <Dicionario/>
            <Fonte Estilo="1" Nome="Arial" Tamanho="12"/>
            <Ancorado Valor="false"/>
            <TamanhoAutmatico Valor="true"/>
            <Card Valor="1"/>
            <MovimentacaoManual Valor="false"/>
            <Papel Valor=""/>
            <Fonte Estilo="1" Nome="Arial" Tamanho="12"/>
        </LogicoCardinalidade>
    </LogicoLinha>
    <LogicoLinha ID="15">
        <DisablePainted Valor="false"/>
        <Tag LinhaMestre="-1"/>
        <Dashed Valor="false"/>
        <Ancorado Valor="false"/>
        <TemSetaPontaA Valor="false"/>
        <TemSetaPontaB Valor="true"/>
        <SetaAberta Valor="true"/>
        <SetaLargura Valor="10"/>
        <Inteligente Valor="true"/>
        <SetaAutomatica Valor="true"/>
        <Largura Valor="1"/>
        <Ligacoes PontaA="3" PontaB="9"/>
        <Pontos>
            <Ponto Left="626" Top="666"/>
            <Ponto Left="723" Top="666"/>
            <Ponto Left="723" Top="895"/>
            <Ponto Left="819" Top="895"/>
        </Pontos>
        <LogicoCardinalidade ID="16">
            <Bounds Height="14" Left="636" Top="654" Width="39"/>
            <DisablePainted Valor="false"/>
            <Texto>Cardinalidade_3</Texto>
            <Observacao/>
            <Dicionario/>
            <Fonte Estilo="1" Nome="Arial" Tamanho="12"/>
            <Ancorado Valor="false"/>
            <TamanhoAutmatico Valor="true"/>
            <Card Valor="0"/>
            <MovimentacaoManual Valor="false"/>
            <Papel Valor=""/>
            <Fonte Estilo="1" Nome="Arial" Tamanho="12"/>
        </LogicoCardinalidade>
        <LogicoCardinalidade ID="17">
            <Bounds Height="14" Left="776" Top="883" Width="39"/>
            <DisablePainted Valor="false"/>
            <Texto>Cardinalidade_4</Texto>
            <Observacao/>
            <Dicionario/>
            <Fonte Estilo="1" Nome="Arial" Tamanho="12"/>
            <Ancorado Valor="false"/>
            <TamanhoAutmatico Valor="true"/>
            <Card Valor="1"/>
            <MovimentacaoManual Valor="false"/>
            <Papel Valor=""/>
            <Fonte Estilo="1" Nome="Arial" Tamanho="12"/>
        </LogicoCardinalidade>
    </LogicoLinha>
    <LogicoLinha ID="18">
        <DisablePainted Valor="false"/>
        <Tag LinhaMestre="-1"/>
        <Dashed Valor="false"/>
        <Ancorado Valor="false"/>
        <TemSetaPontaA Valor="false"/>
        <TemSetaPontaB Valor="true"/>
        <SetaAberta Valor="true"/>
        <SetaLargura Valor="10"/>
        <Inteligente Valor="true"/>
        <SetaAutomatica Valor="true"/>
        <Largura Valor="1"/>
        <Ligacoes PontaA="3" PontaB="10"/>
        <Pontos>
            <Ponto Left="574" Top="738"/>
            <Ponto Left="574" Top="881"/>
            <Ponto Left="588" Top="881"/>
            <Ponto Left="588" Top="1024"/>
        </Pontos>
        <LogicoCardinalidade ID="19">
            <Bounds Height="14" Left="537" Top="748" Width="39"/>
            <DisablePainted Valor="false"/>
            <Texto>Cardinalidade_5</Texto>
            <Observacao/>
            <Dicionario/>
            <Fonte Estilo="1" Nome="Arial" Tamanho="12"/>
            <Ancorado Valor="false"/>
            <TamanhoAutmatico Valor="true"/>
            <Card Valor="0"/>
            <MovimentacaoManual Valor="false"/>
            <Papel Valor=""/>
            <Fonte Estilo="1" Nome="Arial" Tamanho="12"/>
        </LogicoCardinalidade>
        <LogicoCardinalidade ID="20">
            <Bounds Height="14" Left="551" Top="1006" Width="39"/>
            <DisablePainted Valor="false"/>
            <Texto>Cardinalidade_6</Texto>
            <Observacao/>
            <Dicionario/>
            <Fonte Estilo="1" Nome="Arial" Tamanho="12"/>
            <Ancorado Valor="false"/>
            <TamanhoAutmatico Valor="true"/>
            <Card Valor="1"/>
            <MovimentacaoManual Valor="false"/>
            <Papel Valor=""/>
            <Fonte Estilo="1" Nome="Arial" Tamanho="12"/>
        </LogicoCardinalidade>
    </LogicoLinha>
    <LogicoLinha ID="21">
        <DisablePainted Valor="false"/>
        <Tag LinhaMestre="-1"/>
        <Dashed Valor="false"/>
        <Ancorado Valor="false"/>
        <TemSetaPontaA Valor="false"/>
        <TemSetaPontaB Valor="true"/>
        <SetaAberta Valor="true"/>
        <SetaLargura Valor="10"/>
        <Inteligente Valor="true"/>
        <SetaAutomatica Valor="true"/>
        <Largura Valor="1"/>
        <Ligacoes PontaA="3" PontaB="2"/>
        <Pontos>
            <Ponto Left="554" Top="588"/>
            <Ponto Left="554" Top="533"/>
            <Ponto Left="614" Top="533"/>
            <Ponto Left="614" Top="477"/>
        </Pontos>
        <LogicoCardinalidade ID="22">
            <Bounds Height="14" Left="517" Top="570" Width="39"/>
            <DisablePainted Valor="false"/>
            <Texto>Cardinalidade_7</Texto>
            <Observacao/>
            <Dicionario/>
            <Fonte Estilo="1" Nome="Arial" Tamanho="12"/>
            <Ancorado Valor="false"/>
            <TamanhoAutmatico Valor="true"/>
            <Card Valor="0"/>
            <MovimentacaoManual Valor="false"/>
            <Papel Valor=""/>
            <Fonte Estilo="1" Nome="Arial" Tamanho="12"/>
        </LogicoCardinalidade>
        <LogicoCardinalidade ID="23">
            <Bounds Height="14" Left="576" Top="487" Width="40"/>
            <DisablePainted Valor="false"/>
            <Texto>Cardinalidade_8</Texto>
            <Observacao/>
            <Dicionario/>
            <Fonte Estilo="1" Nome="Arial" Tamanho="12"/>
            <Ancorado Valor="false"/>
            <TamanhoAutmatico Valor="true"/>
            <Card Valor="2"/>
            <MovimentacaoManual Valor="false"/>
            <Papel Valor=""/>
            <Fonte Estilo="1" Nome="Arial" Tamanho="12"/>
        </LogicoCardinalidade>
    </LogicoLinha>
    <LogicoLinha ID="24">
        <DisablePainted Valor="false"/>
        <Tag LinhaMestre="-1"/>
        <Dashed Valor="false"/>
        <Ancorado Valor="false"/>
        <TemSetaPontaA Valor="false"/>
        <TemSetaPontaB Valor="true"/>
        <SetaAberta Valor="true"/>
        <SetaLargura Valor="10"/>
        <Inteligente Valor="true"/>
        <SetaAutomatica Valor="true"/>
        <Largura Valor="1"/>
        <Ligacoes PontaA="5" PontaB="4"/>
        <Pontos>
            <Ponto Left="1208" Top="603"/>
            <Ponto Left="1208" Top="505"/>
            <Ponto Left="1208" Top="505"/>
            <Ponto Left="1208" Top="407"/>
        </Pontos>
        <LogicoCardinalidade ID="25">
            <Bounds Height="14" Left="1171" Top="585" Width="39"/>
            <DisablePainted Valor="false"/>
            <Texto>Cardinalidade_9</Texto>
            <Observacao/>
            <Dicionario/>
            <Fonte Estilo="1" Nome="Arial" Tamanho="12"/>
            <Ancorado Valor="false"/>
            <TamanhoAutmatico Valor="true"/>
            <Card Valor="0"/>
            <MovimentacaoManual Valor="false"/>
            <Papel Valor=""/>
            <Fonte Estilo="1" Nome="Arial" Tamanho="12"/>
        </LogicoCardinalidade>
        <LogicoCardinalidade ID="26">
            <Bounds Height="14" Left="1170" Top="417" Width="40"/>
            <DisablePainted Valor="false"/>
            <Texto>Cardinalidade_10</Texto>
            <Observacao/>
            <Dicionario/>
            <Fonte Estilo="1" Nome="Arial" Tamanho="12"/>
            <Ancorado Valor="false"/>
            <TamanhoAutmatico Valor="true"/>
            <Card Valor="2"/>
            <MovimentacaoManual Valor="false"/>
            <Papel Valor=""/>
            <Fonte Estilo="1" Nome="Arial" Tamanho="12"/>
        </LogicoCardinalidade>
    </LogicoLinha>
    <LogicoLinha ID="27">
        <DisablePainted Valor="false"/>
        <Tag LinhaMestre="-1"/>
        <Dashed Valor="false"/>
        <Ancorado Valor="false"/>
        <TemSetaPontaA Valor="false"/>
        <TemSetaPontaB Valor="true"/>
        <SetaAberta Valor="true"/>
        <SetaLargura Valor="10"/>
        <Inteligente Valor="true"/>
        <SetaAutomatica Valor="true"/>
        <Largura Valor="1"/>
        <Ligacoes PontaA="6" PontaB="4"/>
        <Pontos>
            <Ponto Left="1448" Top="273"/>
            <Ponto Left="1391" Top="273"/>
            <Ponto Left="1391" Top="285"/>
            <Ponto Left="1333" Top="285"/>
        </Pontos>
        <LogicoCardinalidade ID="28">
            <Bounds Height="14" Left="1405" Top="261" Width="39"/>
            <DisablePainted Valor="false"/>
            <Texto>Cardinalidade_11</Texto>
            <Observacao/>
            <Dicionario/>
            <Fonte Estilo="1" Nome="Arial" Tamanho="12"/>
            <Ancorado Valor="false"/>
            <TamanhoAutmatico Valor="true"/>
            <Card Valor="0"/>
            <MovimentacaoManual Valor="false"/>
            <Papel Valor=""/>
            <Fonte Estilo="1" Nome="Arial" Tamanho="12"/>
        </LogicoCardinalidade>
        <LogicoCardinalidade ID="29">
            <Bounds Height="14" Left="1343" Top="273" Width="40"/>
            <DisablePainted Valor="false"/>
            <Texto>Cardinalidade_12</Texto>
            <Observacao/>
            <Dicionario/>
            <Fonte Estilo="1" Nome="Arial" Tamanho="12"/>
            <Ancorado Valor="false"/>
            <TamanhoAutmatico Valor="true"/>
            <Card Valor="2"/>
            <MovimentacaoManual Valor="false"/>
            <Papel Valor=""/>
            <Fonte Estilo="1" Nome="Arial" Tamanho="12"/>
        </LogicoCardinalidade>
    </LogicoLinha>
    <LogicoLinha ID="30">
        <DisablePainted Valor="false"/>
        <Tag LinhaMestre="-1"/>
        <Dashed Valor="false"/>
        <Ancorado Valor="false"/>
        <TemSetaPontaA Valor="false"/>
        <TemSetaPontaB Valor="true"/>
        <SetaAberta Valor="true"/>
        <SetaLargura Valor="10"/>
        <Inteligente Valor="true"/>
        <SetaAutomatica Valor="true"/>
        <Largura Valor="1"/>
        <Ligacoes PontaA="7" PontaB="4"/>
        <Pontos>
            <Ponto Left="1498" Top="611"/>
            <Ponto Left="1416" Top="611"/>
            <Ponto Left="1416" Top="342"/>
            <Ponto Left="1333" Top="342"/>
        </Pontos>
        <LogicoCardinalidade ID="31">
            <Bounds Height="14" Left="1455" Top="599" Width="39"/>
            <DisablePainted Valor="false"/>
            <Texto>Cardinalidade_13</Texto>
            <Observacao/>
            <Dicionario/>
            <Fonte Estilo="1" Nome="Arial" Tamanho="12"/>
            <Ancorado Valor="false"/>
            <TamanhoAutmatico Valor="true"/>
            <Card Valor="0"/>
            <MovimentacaoManual Valor="false"/>
            <Papel Valor=""/>
            <Fonte Estilo="1" Nome="Arial" Tamanho="12"/>
        </LogicoCardinalidade>
        <LogicoCardinalidade ID="32">
            <Bounds Height="14" Left="1343" Top="330" Width="40"/>
            <DisablePainted Valor="false"/>
            <Texto>Cardinalidade_14</Texto>
            <Observacao/>
            <Dicionario/>
            <Fonte Estilo="1" Nome="Arial" Tamanho="12"/>
            <Ancorado Valor="false"/>
            <TamanhoAutmatico Valor="true"/>
            <Card Valor="2"/>
            <MovimentacaoManual Valor="false"/>
            <Papel Valor=""/>
            <Fonte Estilo="1" Nome="Arial" Tamanho="12"/>
        </LogicoCardinalidade>
    </LogicoLinha>
    <LogicoLinha ID="34">
        <DisablePainted Valor="false"/>
        <Tag LinhaMestre="-1"/>
        <Dashed Valor="false"/>
        <Ancorado Valor="false"/>
        <TemSetaPontaA Valor="true"/>
        <TemSetaPontaB Valor="false"/>
        <SetaAberta Valor="true"/>
        <SetaLargura Valor="10"/>
        <Inteligente Valor="true"/>
        <SetaAutomatica Valor="true"/>
        <Largura Valor="1"/>
        <Ligacoes PontaA="11" PontaB="2"/>
        <Pontos>
            <Ponto Left="819" Top="394"/>
            <Ponto Left="757" Top="394"/>
            <Ponto Left="757" Top="405"/>
            <Ponto Left="695" Top="405"/>
        </Pontos>
        <LogicoCardinalidade ID="35">
            <Bounds Height="14" Left="775" Top="382" Width="40"/>
            <DisablePainted Valor="false"/>
            <Texto>Cardinalidade_15</Texto>
            <Observacao/>
            <Dicionario/>
            <Fonte Estilo="1" Nome="Arial" Tamanho="12"/>
            <Ancorado Valor="false"/>
            <TamanhoAutmatico Valor="true"/>
            <Card Valor="2"/>
            <MovimentacaoManual Valor="false"/>
            <Papel Valor=""/>
            <Fonte Estilo="1" Nome="Arial" Tamanho="12"/>
        </LogicoCardinalidade>
        <LogicoCardinalidade ID="36">
            <Bounds Height="14" Left="705" Top="393" Width="39"/>
            <DisablePainted Valor="false"/>
            <Texto>Cardinalidade_16</Texto>
            <Observacao/>
            <Dicionario/>
            <Fonte Estilo="1" Nome="Arial" Tamanho="12"/>
            <Ancorado Valor="false"/>
            <TamanhoAutmatico Valor="true"/>
            <Card Valor="0"/>
            <MovimentacaoManual Valor="false"/>
            <Papel Valor=""/>
            <Fonte Estilo="1" Nome="Arial" Tamanho="12"/>
        </LogicoCardinalidade>
    </LogicoLinha>
    <LogicoLinha ID="37">
        <DisablePainted Valor="false"/>
        <Tag LinhaMestre="-1"/>
        <Dashed Valor="false"/>
        <Ancorado Valor="false"/>
        <TemSetaPontaA Valor="true"/>
        <TemSetaPontaB Valor="false"/>
        <SetaAberta Valor="true"/>
        <SetaLargura Valor="10"/>
        <Inteligente Valor="true"/>
        <SetaAutomatica Valor="true"/>
        <Largura Valor="1"/>
        <Ligacoes PontaA="11" PontaB="4"/>
        <Pontos>
            <Ponto Left="1044" Top="394"/>
            <Ponto Left="1087" Top="394"/>
            <Ponto Left="1087" Top="313"/>
            <Ponto Left="1129" Top="313"/>
        </Pontos>
        <LogicoCardinalidade ID="38">
            <Bounds Height="14" Left="1054" Top="382" Width="40"/>
            <DisablePainted Valor="false"/>
            <Texto>Cardinalidade_17</Texto>
            <Observacao/>
            <Dicionario/>
            <Fonte Estilo="1" Nome="Arial" Tamanho="12"/>
            <Ancorado Valor="false"/>
            <TamanhoAutmatico Valor="true"/>
            <Card Valor="2"/>
            <MovimentacaoManual Valor="false"/>
            <Papel Valor=""/>
            <Fonte Estilo="1" Nome="Arial" Tamanho="12"/>
        </LogicoCardinalidade>
        <LogicoCardinalidade ID="39">
            <Bounds Height="14" Left="1086" Top="301" Width="39"/>
            <DisablePainted Valor="false"/>
            <Texto>Cardinalidade_18</Texto>
            <Observacao/>
            <Dicionario/>
            <Fonte Estilo="1" Nome="Arial" Tamanho="12"/>
            <Ancorado Valor="false"/>
            <TamanhoAutmatico Valor="true"/>
            <Card Valor="0"/>
            <MovimentacaoManual Valor="false"/>
            <Papel Valor=""/>
            <Fonte Estilo="1" Nome="Arial" Tamanho="12"/>
        </LogicoCardinalidade>
    </LogicoLinha>
    <Tabela ID="39">
        <Bounds Height="193" Left="571" Top="76" Width="150"/>
        <DisablePainted Valor="false"/>
        <Texto>delivery_status</Texto>
        <Observacao/>
        <Dicionario/>
        <Fonte Estilo="1" Nome="Arial" Tamanho="12"/>
        <Ancorado Valor="false"/>
        <Delimite Valor="true"/>
        <Roundrect Valor="22"/>
        <Gradiente Valor="true"/>
        <GradienteStartColor Valor="0,0,0,255"/>
        <GradienteEndColor Valor="204,204,204,255"/>
        <CorBorda Valor="0,0,0,255"/>
        <GDirecao Valor="0"/>
        <Alfa Valor="25"/>
        <Autosize Valor="true"/>
        <Gradiente Valor="true"/>
        <GradienteStartColor Valor="0,0,0,255"/>
        <GradienteEndColor Valor="204,204,204,255"/>
        <GDirecao Valor="0"/>
        <Alfa Valor="25"/>
        <ShowDDL Valor="false"/>
        <ShowInPlain Valor="false"/>
        <MostrarConstraints Valor="true"/>
        <PlainIR Valor="true"/>
        <Campos>
            <Campo>
                <Texto>delivery_status_PK</Texto>
                <Tipo>INT</Tipo>
                <Complemento>NOT NULL</Complemento>
                <Dicionario/>
                <Observacao/>
                <Key Valor="true"/>
                <Fkey Valor="false"/>
                <Unique Valor="false"/>
            </Campo>
            <Campo>
                <Texto>placed</Texto>
                <Tipo>String(3)</Tipo>
                <Complemento/>
                <Dicionario/>
                <Observacao/>
                <Key Valor="false"/>
                <Fkey Valor="false"/>
                <Unique Valor="false"/>
            </Campo>
            <Campo>
                <Texto>dispatched</Texto>
                <Tipo>String(10)</Tipo>
                <Complemento/>
                <Dicionario/>
                <Observacao/>
                <Key Valor="false"/>
                <Fkey Valor="false"/>
                <Unique Valor="false"/>
            </Campo>
            <Campo>
                <Texto>delivered</Texto>
                <Tipo>String(3)</Tipo>
                <Complemento/>
                <Dicionario/>
                <Observacao/>
                <Key Valor="false"/>
                <Fkey Valor="false"/>
                <Unique Valor="false"/>
            </Campo>
            <Campo>
                <Texto>ready_pickup</Texto>
                <Tipo>String(3)</Tipo>
                <Complemento/>
                <Dicionario/>
                <Observacao/>
                <Key Valor="false"/>
                <Fkey Valor="false"/>
                <Unique Valor="false"/>
            </Campo>
            <Campo>
                <Texto>canceled</Texto>
                <Tipo>Number(3)</Tipo>
                <Complemento/>
                <Dicionario/>
                <Observacao/>
                <Key Valor="false"/>
                <Fkey Valor="false"/>
                <Unique Valor="false"/>
            </Campo>
        </Campos>
        <Constraints>
            <Constraint>
                <Nome Valor=""/>
                <Nomeada Valor="false"/>
                <Tipo Valor="0"/>
                <Dicionario/>
                <Observacao/>
                <DdlOnUpdate/>
                <DdlOnDelete/>
                <LigacaoParaOrigem ID="-1"/>
                <ConstraintOrigem CamposDestino="[-1]" CamposOrigem="[0]" ID="-1,-1"/>
            </Constraint>
        </Constraints>
    </Tabela>
    <LogicoLinha ID="44">
        <DisablePainted Valor="false"/>
        <Tag LinhaMestre="-1"/>
        <Dashed Valor="false"/>
        <Ancorado Valor="false"/>
        <TemSetaPontaA Valor="false"/>
        <TemSetaPontaB Valor="true"/>
        <SetaAberta Valor="true"/>
        <SetaLargura Valor="10"/>
        <Inteligente Valor="true"/>
        <SetaAutomatica Valor="true"/>
        <Largura Valor="1"/>
        <Ligacoes PontaA="2" PontaB="39"/>
        <Pontos>
            <Ponto Left="535" Top="407"/>
            <Ponto Left="526" Top="407"/>
            <Ponto Left="526" Top="233"/>
            <Ponto Left="567" Top="233"/>
        </Pontos>
        <LogicoCardinalidade ID="45">
            <Bounds Height="14" Left="492" Top="395" Width="39"/>
            <DisablePainted Valor="false"/>
            <Texto>Cardinalidade_19</Texto>
            <Observacao/>
            <Dicionario/>
            <Fonte Estilo="1" Nome="Arial" Tamanho="12"/>
            <Ancorado Valor="false"/>
            <TamanhoAutmatico Valor="true"/>
            <Card Valor="1"/>
            <MovimentacaoManual Valor="false"/>
            <Papel Valor=""/>
            <Fonte Estilo="1" Nome="Arial" Tamanho="12"/>
        </LogicoCardinalidade>
        <LogicoCardinalidade ID="46">
            <Bounds Height="14" Left="523" Top="221" Width="40"/>
            <DisablePainted Valor="false"/>
            <Texto>Cardinalidade_20</Texto>
            <Observacao/>
            <Dicionario/>
            <Fonte Estilo="1" Nome="Arial" Tamanho="12"/>
            <Ancorado Valor="false"/>
            <TamanhoAutmatico Valor="true"/>
            <Card Valor="3"/>
            <MovimentacaoManual Valor="false"/>
            <Papel Valor=""/>
            <Fonte Estilo="1" Nome="Arial" Tamanho="12"/>
        </LogicoCardinalidade>
    </LogicoLinha>
</DIAGRAMA>
